week3/week3_q2.v
module shift_register_8_bit(
    input[7:0] in,
    input clk, ld, asr, lsl, clr,
    output reg[7:0] out
);
    always @(posedge clk) begin
        if (clr) begin
            out <= 8'b0;
        end
        else if (ld) begin
            out <= in;
        end
        else if (asr) begin
            out <= {out[7], out[7:1]};
        end
        else if (lsl) begin
            out <= {out[6:0], 1'b0};
        end
    end
endmodule

week3/week3_q2_tb.v
module shift_register_8_bit_tb;
    reg [7:0] in;
    reg clk = 0;
    reg ld, asr, lsl, clr;
    wire [7:0] out;

    shift_register_8_bit DUT (
        .in(in),
        .clk(clk),
        .ld(ld),
        .asr(asr),
        .lsl(lsl),
        .clr(clr),
        .out(out)
    );

    initial begin
        forever #5 clk = ~clk;
    end

    initial begin
        $dumpfile("shift_reg_tb.vcd");
        $dumpvars(0, shift_register_8_bit_tb);
        $monitor($time, " in=%b, clr=%b, ld=%b, asr=%b, lsl=%b, out=%b", in, clr, ld, asr, lsl, out);

        in = 8'b0;
        clr = 0; ld = 0; asr = 0; lsl = 0;

        #10 in = 8'b10000011; ld = 1;
        #10 ld = 0; asr = 1; lsl = 0; clr = 0;
        #20 in = 8'b00111010; ld = 1; // after 20 seconds for 2 right shifts
        #10 ld = 0; asr = 0; lsl = 1; clr = 0;
        #20 ld = 0; asr = 0; lsl = 0; clr = 1; // after 20 seconds for 2 left shifts
        #10 $finish;
    end
endmodule

week3/shift_reg_tb.vcd
$date
	Tue Jun 30 20:35:24 2026
$end
$version
	Icarus Verilog
$end
$timescale
	1s
$end
$scope module shift_register_8_bit_tb $end
$var wire 8 ! out [7:0] $end
$var reg 1 " asr $end
$var reg 1 # clk $end
$var reg 1 $ clr $end
$var reg 8 % in [7:0] $end
$var reg 1 & ld $end
$var reg 1 ' lsl $end
$scope module DUT $end
$var wire 1 " asr $end
$var wire 1 # clk $end
$var wire 1 $ clr $end
$var wire 8 ( in [7:0] $end
$var wire 1 & ld $end
$var wire 1 ' lsl $end
$var reg 8 ) out [7:0] $end
$upscope $end
$upscope $end
$enddefinitions $end
$comment Show the parameter values. $end
$dumpall
$end
#0
$dumpvars
bx )
b0 (
0'
0&
b0 %
0$
0#
0"
bx !
$end
#5
1#
#10
0#
1&
b10000011 %
b10000011 (
#15
b10000011 !
b10000011 )
1#
#20
0#
1"
0&
#25
b11000001 !
b11000001 )
1#
#30
0#
#35
b11100000 !
b11100000 )
1#
#40
0#
1&
b111010 %
b111010 (
#45
b111010 !
b111010 )
1#
#50
0#
1'
0"
0&
#55
b1110100 !
b1110100 )
1#
#60
0#
#65
b11101000 !
b11101000 )
1#
#70
0#
1$
0'
#75
b0 !
b0 )
1#
