week8/processor.v
module MIPS32 # (
    // R-type instructions
    parameter [5:0] ADD = 6'b000000, SUB = 6'b000001, AND = 6'b000010, OR = 6'b000011,
    parameter [5:0] SLT = 6'b000100, MUL = 6'b000101, HLT = 6'b111111,

    // I-type instructions
    parameter [5:0] LW = 6'b001000, SW = 6'b001001,
    parameter [5:0] ADDI = 6'b001010, SUBI = 6'b001011, SLTI = 6'b001100,
    parameter [5:0] BNEQZ = 6'b001101, BEQZ = 6'b001110,

    // J-type instructions
    parameter [5:0] J = 6'b010000,

    // Instruction types
    parameter [2:0] R = 3'b000, I = 3'b001, LOAD = 3'b010, STORE = 3'b011, 
    parameter [2:0] BRANCH = 3'b100, JUMP = 3'b101, HALT = 3'b110
) (
    input clk1,
    input clk2
);
    reg [31:0] PC;
    reg [31:0] IF_ID_IR, IF_ID_NPC;
    reg [31:0] ID_EX_IR, ID_EX_NPC, ID_EX_A, ID_EX_B, ID_EX_IMM;
    reg [31:0] EX_MEM_IR, EX_MEM_ALU_OUT, EX_MEM_B;
    reg EX_MEM_COND;
    reg [31:0] MEM_WB_IR, MEM_WB_ALU_OUT, MEM_WB_LMD;

    reg [2:0] ID_EX_TYPE, EX_MEM_TYPE, MEM_WB_TYPE;

    reg HALTED, TAKEN_BRANCH;

    reg [31:0] reg_file [0:31];
    reg [31:0] mem [0:1023];

    // Stage 1: Instruction Fetch (IF)
    always @(posedge clk1) begin
        if (!HALTED) begin
            if ((EX_MEM_IR[31:26] == BEQZ && EX_MEM_COND == 1'b1)
            ||  (EX_MEM_IR[31:26] == BNEQZ && EX_MEM_COND == 1'b0)
            ||  (EX_MEM_TYPE == JUMP)) begin
                TAKEN_BRANCH <= 1'b1;
                IF_ID_IR <= mem[EX_MEM_ALU_OUT];
                IF_ID_NPC <= EX_MEM_ALU_OUT + 1;
                PC <= EX_MEM_ALU_OUT + 1;
            end else begin
                TAKEN_BRANCH <= 1'b0;
                IF_ID_IR <= mem[PC];
                IF_ID_NPC <= PC + 1;
                PC <= PC + 1;
            end
        end
    end

    // Stage 2: Instruction Decode (ID)
    always @(posedge clk2) begin
        if (!HALTED) begin
            ID_EX_IR <= IF_ID_IR;
            ID_EX_NPC <= IF_ID_NPC;

            ID_EX_A <= reg_file[IF_ID_IR[25:21]];
            ID_EX_B <= reg_file[IF_ID_IR[20:16]];
            ID_EX_IMM <= {{16{IF_ID_IR[15]}}, IF_ID_IR[15:0]};

            case (IF_ID_IR[31:26])
                ADD, SUB, AND, OR, SLT, MUL : ID_EX_TYPE <= R;
                ADDI, SUBI, SLTI : ID_EX_TYPE <= I;
                LW : ID_EX_TYPE <= LOAD;
                SW : ID_EX_TYPE <= STORE;
                BEQZ, BNEQZ : ID_EX_TYPE <= BRANCH;
                J : ID_EX_TYPE <= JUMP;
                HLT : ID_EX_TYPE <= HALT;
                default : ID_EX_TYPE <= HALT;
            endcase
        end
    end

    // Stage 3: Execute (EX)
    always @(posedge clk1) begin
        if (!HALTED) begin
            EX_MEM_TYPE <= ID_EX_TYPE;
            EX_MEM_IR <= ID_EX_IR;
            EX_MEM_B <= ID_EX_B;

            case (ID_EX_TYPE)
                R : begin
                    case (ID_EX_IR[31:26])
                        ADD : EX_MEM_ALU_OUT <= ID_EX_A + ID_EX_B;
                        SUB : EX_MEM_ALU_OUT <= ID_EX_A - ID_EX_B;
                        AND : EX_MEM_ALU_OUT <= ID_EX_A & ID_EX_B;
                        OR  : EX_MEM_ALU_OUT <= ID_EX_A | ID_EX_B;
                        SLT : EX_MEM_ALU_OUT <= ID_EX_A < ID_EX_B;
                        MUL : EX_MEM_ALU_OUT <= ID_EX_A * ID_EX_B;
                        default : EX_MEM_ALU_OUT <= 32'hxxxxxxxx;
                    endcase
                end

                I : begin
                    case (ID_EX_IR[31:26])
                        ADDI : EX_MEM_ALU_OUT <= ID_EX_A + ID_EX_IMM;
                        SUBI : EX_MEM_ALU_OUT <= ID_EX_A - ID_EX_IMM;
                        SLTI : EX_MEM_ALU_OUT <= ID_EX_A < ID_EX_B;
                        default: EX_MEM_ALU_OUT <= 32'hxxxxxxxx;
                    endcase
                end

                LOAD, STORE : begin
                    EX_MEM_ALU_OUT <= ID_EX_A + ID_EX_IMM;
                end

                BRANCH : begin
                    EX_MEM_ALU_OUT <= ID_EX_NPC + ID_EX_IMM;
                    EX_MEM_COND <= (ID_EX_A == 0);
                end

                JUMP : begin
                    EX_MEM_ALU_OUT <= ID_EX_NPC + ID_EX_IMM;
                end
            endcase
        end
    end

    // Stage 4: Memory Access (Mem)
    always @(posedge clk2) begin
        // MEM_WB_LMD
        if (!HALTED) begin
            MEM_WB_IR <= EX_MEM_IR;
            MEM_WB_TYPE <= EX_MEM_TYPE;

            case (EX_MEM_TYPE)
                R, I : MEM_WB_ALU_OUT <= EX_MEM_ALU_OUT;
                LOAD : MEM_WB_LMD <= mem[EX_MEM_ALU_OUT];
                STORE : if (!TAKEN_BRANCH) mem[EX_MEM_ALU_OUT] <= EX_MEM_B;
            endcase
        end
    end

    // Stage 5: Write back (WB)
    always @(posedge clk1) begin
        if (!TAKEN_BRANCH) begin
            case (MEM_WB_TYPE)
                R : if (MEM_WB_IR[15:11] != 0) reg_file[MEM_WB_IR[15:11]] <= MEM_WB_ALU_OUT;
                I : if (MEM_WB_IR[20:16] != 0) reg_file[MEM_WB_IR[20:16]] <= MEM_WB_ALU_OUT;
                LOAD : if (MEM_WB_IR[20:16] != 0) reg_file[MEM_WB_IR[20:16]] <= MEM_WB_LMD;
                HALT : HALTED <= 1'b1;
            endcase
        end
    end
endmodule

week8/testbench2.v
module testbench2;
    // Load a program from a specific memory address (e.g. 0)
    // Initialize PC to the address of the first instruction (0)

    initial begin
        $dumpfile("mips_test2.vcd");
        $dumpvars(0, testbench2);
        #600 $finish;
    end

    reg clk1, clk2;
    initial begin
        clk1 = 0; clk2 = 0;
        repeat (25) begin
            #5 clk1 = 1'b1; #5 clk1 = 1'b0;
            #5 clk2 = 1'b1; #5 clk2 = 1'b0;
        end
    end

    MIPS32 processor (
        .clk1(clk1),
        .clk2(clk2)
    );

    integer k;
    initial begin
        for (k = 0; k < 32; k = k + 1) begin
            processor.reg_file[k] = k;
        end

        processor.mem[120] = 32'd85;

        processor.mem[0] = 32'b00101000000000010000000001111000; // ADDI R1, R0, 120
        processor.mem[1] = 32'b00001100110001100011000000000000; // OR   R6, R6, R6 - Dummy instruction to avoid RAW Data Hazard
        processor.mem[2] = 32'b00100000001000100000000000000000; // LW   R2, 0(R1)
        processor.mem[3] = 32'b00001100110001100011000000000000; // OR   R6, R6, R6 - Dummy instruction to avoid RAW Data Hazard
        processor.mem[4] = 32'b00101000010000110000000000101101; // ADDI R3, R2, 45
        processor.mem[5] = 32'b00001100110001100011000000000000; // OR   R6, R6, R6 - Dummy instruction to avoid RAW Data Hazard
        processor.mem[6] = 32'b00100100001000110000000000000001; // SW   R3, 1(R1)
        processor.mem[7] = 32'b11111100000000000000000000000000; // HALT

        processor.PC = 1'b0;
        processor.HALTED = 1'b0;
        processor.TAKEN_BRANCH = 1'b0;

        #500;
        $display("MEM[120] = %0d", processor.mem[120]);
        $display("MEM[121] = %0d", processor.mem[121]);
        check();
    end

    task check();
    reg [31:0] expected;
        begin
            expected = processor.mem[120] + 45;
            if (processor.mem[121] != expected) begin
                $display("FAILED | Expected : %0d | Got : %0d",
                        expected, processor.mem[121]);
            end else begin
                $display("PASSED | Expected : %0d | Got : %0d",
                        expected, processor.mem[121]);
            end
        end
    endtask
endmodule

week8/mips_test2.vcd
$date
	Sat Jul 25 16:33:53 2026
$end
$version
	Icarus Verilog
$end
$timescale
	1s
$end
$scope module testbench2 $end
$var reg 1 ! clk1 $end
$var reg 1 " clk2 $end
$var integer 32 # k [31:0] $end
$scope module processor $end
$var wire 1 ! clk1 $end
$var wire 1 " clk2 $end
$var parameter 6 $ ADD $end
$var parameter 6 % ADDI $end
$var parameter 6 & AND $end
$var parameter 6 ' BEQZ $end
$var parameter 6 ( BNEQZ $end
$var parameter 3 ) BRANCH $end
$var parameter 3 * HALT $end
$var parameter 6 + HLT $end
$var parameter 3 , I $end
$var parameter 6 - J $end
$var parameter 3 . JUMP $end
$var parameter 3 / LOAD $end
$var parameter 6 0 LW $end
$var parameter 6 1 MUL $end
$var parameter 6 2 OR $end
$var parameter 3 3 R $end
$var parameter 6 4 SLT $end
$var parameter 6 5 SLTI $end
$var parameter 3 6 STORE $end
$var parameter 6 7 SUB $end
$var parameter 6 8 SUBI $end
$var parameter 6 9 SW $end
$var reg 32 : EX_MEM_ALU_OUT [31:0] $end
$var reg 32 ; EX_MEM_B [31:0] $end
$var reg 1 < EX_MEM_COND $end
$var reg 32 = EX_MEM_IR [31:0] $end
$var reg 3 > EX_MEM_TYPE [2:0] $end
$var reg 1 ? HALTED $end
$var reg 32 @ ID_EX_A [31:0] $end
$var reg 32 A ID_EX_B [31:0] $end
$var reg 32 B ID_EX_IMM [31:0] $end
$var reg 32 C ID_EX_IR [31:0] $end
$var reg 32 D ID_EX_NPC [31:0] $end
$var reg 3 E ID_EX_TYPE [2:0] $end
$var reg 32 F IF_ID_IR [31:0] $end
$var reg 32 G IF_ID_NPC [31:0] $end
$var reg 32 H MEM_WB_ALU_OUT [31:0] $end
$var reg 32 I MEM_WB_IR [31:0] $end
$var reg 32 J MEM_WB_LMD [31:0] $end
$var reg 3 K MEM_WB_TYPE [2:0] $end
$var reg 32 L PC [31:0] $end
$var reg 1 M TAKEN_BRANCH $end
$upscope $end
$scope task check $end
$var reg 32 N expected [31:0] $end
$upscope $end
$upscope $end
$enddefinitions $end
$comment Show the parameter values. $end
$dumpall
b1001 9
b1011 8
b1 7
b11 6
b1100 5
b100 4
b0 3
b11 2
b101 1
b1000 0
b10 /
b101 .
b10000 -
b1 ,
b111111 +
b110 *
b100 )
b1101 (
b1110 '
b10 &
b1010 %
b0 $
$end
#0
$dumpvars
bx N
0M
b0 L
bx K
bx J
bx I
bx H
bx G
bx F
bx E
bx D
bx C
bx B
bx A
bx @
0?
bx >
bx =
x<
bx ;
bx :
b100000 #
0"
0!
$end
#5
b1 L
b1 G
b101000000000010000000001111000 F
1!
#10
0!
#15
b1 E
b1111000 B
b1 A
b0 @
b1 D
b101000000000010000000001111000 C
1"
#20
0"
#25
b1111000 :
b1 ;
b101000000000010000000001111000 =
b1 >
b10 L
b10 G
b1100110001100011000000000000 F
1!
#30
0!
#35
b1111000 H
b1 K
b101000000000010000000001111000 I
b0 E
b11000000000000 B
b110 A
b110 @
b10 D
b1100110001100011000000000000 C
1"
#40
0"
#45
b11 L
b11 G
b100000001000100000000000000000 F
b110 :
b110 ;
b1100110001100011000000000000 =
b0 >
1!
#50
0!
#55
b10 E
b0 B
b10 A
b1111000 @
b11 D
b100000001000100000000000000000 C
b110 H
b0 K
b1100110001100011000000000000 I
1"
#60
0"
#65
b1111000 :
b10 ;
b100000001000100000000000000000 =
b10 >
b100 L
b100 G
b1100110001100011000000000000 F
1!
#70
0!
#75
b1010101 J
b10 K
b100000001000100000000000000000 I
b0 E
b11000000000000 B
b110 A
b110 @
b100 D
b1100110001100011000000000000 C
1"
#80
0"
#85
b101 L
b101 G
b101000010000110000000000101101 F
b110 :
b110 ;
b1100110001100011000000000000 =
b0 >
1!
#90
0!
#95
b1 E
b101101 B
b11 A
b1010101 @
b101 D
b101000010000110000000000101101 C
b0 K
b1100110001100011000000000000 I
1"
#100
0"
#105
b10000010 :
b11 ;
b101000010000110000000000101101 =
b1 >
b110 L
b110 G
b1100110001100011000000000000 F
1!
#110
0!
#115
b10000010 H
b1 K
b101000010000110000000000101101 I
b0 E
b11000000000000 B
b110 A
b110 @
b110 D
b1100110001100011000000000000 C
1"
#120
0"
#125
b111 L
b111 G
b100100001000110000000000000001 F
b110 :
b110 ;
b1100110001100011000000000000 =
b0 >
1!
#130
0!
#135
b11 E
b1 B
b10000010 A
b1111000 @
b111 D
b100100001000110000000000000001 C
b110 H
b0 K
b1100110001100011000000000000 I
1"
#140
0"
#145
b1111001 :
b10000010 ;
b100100001000110000000000000001 =
b11 >
b1000 L
b1000 G
b11111100000000000000000000000000 F
1!
#150
0!
#155
b11 K
b100100001000110000000000000001 I
b110 E
b0 B
b0 A
b0 @
b1000 D
b11111100000000000000000000000000 C
1"
#160
0"
#165
b1001 L
b1001 G
bx F
b0 ;
b11111100000000000000000000000000 =
b110 >
1!
#170
0!
#175
bx B
bx A
bx @
b1001 D
bx C
b110 K
b11111100000000000000000000000000 I
1"
#180
0"
#185
1?
bx ;
bx =
b1010 L
b1010 G
1!
