week5/week5_q2.v
module timercontroller (
    output reg x, 
    input b, clk
);
    localparam Off = 2'b00, On1 = 2'b01, On2 = 2'b10, On3 = 2'b11;
    reg [1:0] PS = Off;

    always @(posedge clk) begin
        case (PS)
            Off : PS <= b ? On1 : Off;
            On1 : PS <= On2;
            On2 : PS <= On3;
            On3 : PS <= Off;
        endcase
    end
    
    always @(*) begin
        case (PS)
            Off: x = 1'b0;
            On1, On2, On3: x = 1'b1;
            default: x = 1'b0;
        endcase
    end
endmodule

week5/week5_q2_tb.v
module timer_tb;
    reg clk, b;
    wire x;
    timercontroller timer(.x(x), .b(b), .clk(clk));

    initial begin
        $dumpfile("timer.vcd");
        $dumpvars(0, timer_tb);
        $monitor("b = %b, PS = %b, x = %b", b, timer.PS, x);
        clk = 1'b0;
        #100 $finish;
    end

    always #5 clk = ~clk;

    initial begin
        b = 1'b0;
        #10 b = 1'b1;
        #20 b = 1'b0; // Show that timer doesn't reset once it started
        #30 b = 1'b1; // let b = 0 for the first clock cycle after the timer finishes, 
        // then set it to 1 at the second clock cycle
    end
endmodule

week5/timer.vcd
$date
	Fri Jul 10 14:58:53 2026
$end
$version
	Icarus Verilog
$end
$timescale
	1s
$end
$scope module timer_tb $end
$var wire 1 ! x $end
$var reg 1 " b $end
$var reg 1 # clk $end
$scope module timer $end
$var wire 1 " b $end
$var wire 1 # clk $end
$var parameter 2 $ Off $end
$var parameter 2 % On1 $end
$var parameter 2 & On2 $end
$var parameter 2 ' On3 $end
$var reg 2 ( PS [1:0] $end
$var reg 1 ! x $end
$upscope $end
$upscope $end
$enddefinitions $end
$comment Show the parameter values. $end
$dumpall
b11 '
b10 &
b1 %
b0 $
$end
#0
$dumpvars
b0 (
0#
0"
0!
$end
#5
1#
#10
0#
1"
#15
1!
b1 (
1#
#20
0#
#25
b10 (
1#
#30
0#
0"
#35
b11 (
1#
#40
0#
#45
0!
b0 (
1#
#50
0#
#55
1#
#60
0#
1"
#65
1!
b1 (
1#
#70
0#
#75
b10 (
1#
#80
0#
#85
b11 (
1#
#90
0#
#95
0!
b0 (
1#
